xeger/__init__.py
xeger/xeger.py
py_xeger-0.3.4.dist-info/METADATA
py_xeger-0.3.4.dist-info/WHEEL
py_xeger-0.3.4.dist-info/licenses/LICENSE
py_xeger-0.3.4.dist-info/RECORD
