Metadata-Version: 2.1
Name: py-xeger
Version: 0.3.4
Summary: String generator from Regex
Author-email: Nguyen Khac Thanh <nguyenkhacthanh244@gmail.com>
License-Expression: MIT
License-File: LICENSE
Keywords: regular expressions regexp testing random generator
Classifier: Development Status :: 3 - Alpha
Classifier: Intended Audience :: Developers
Classifier: License :: OSI Approved :: MIT License
Classifier: Programming Language :: Python :: 3.6
Classifier: Programming Language :: Python :: 3.7
Classifier: Programming Language :: Python :: 3.8
Classifier: Programming Language :: Python :: 3.9
Classifier: Programming Language :: Python :: 3.10
Classifier: Programming Language :: Python :: 3.11
Classifier: Topic :: Software Development :: Build Tools
Requires-Python: >=2
Provides-Extra: dev
Requires-Dist: mypy; extra == 'dev'
Requires-Dist: pytest-cov==4.0.0; extra == 'dev'
Requires-Dist: pytest==7.3.1; extra == 'dev'
Requires-Dist: ruff; extra == 'dev'
